rdkit/RDConfig.py
rdkit/RDLogger.py
rdkit/RDPaths.py
rdkit/RDRandom.py
rdkit/TestRunner.py
rdkit/__init__.py
rdkit/conftest.py
rdkit/license.txt
rdkit/pytest.ini
rdkit/rdBase.so
rdkit/Avalon/__init__.py
rdkit/Avalon/pyAvalonTools.so
rdkit/Chem/AllChem.py
rdkit/Chem/BRICS.py
rdkit/Chem/BuildFragmentCatalog.py
rdkit/Chem/ChemicalFeatures.py
rdkit/Chem/ChemicalForceFields.py
rdkit/Chem/Crippen.py
rdkit/Chem/DSViewer.py
rdkit/Chem/Descriptors.py
rdkit/Chem/Descriptors3D.py
rdkit/Chem/EnumerateHeterocycles.py
rdkit/Chem/EnumerateStereoisomers.py
rdkit/Chem/FastSDMolSupplier.py
rdkit/Chem/FeatFinderCLI.py
rdkit/Chem/FilterCatalog.py
rdkit/Chem/FragmentCatalog.py
rdkit/Chem/FragmentMatcher.py
rdkit/Chem/Fragments.py
rdkit/Chem/FunctionalGroups.py
rdkit/Chem/GraphDescriptors.py
rdkit/Chem/Graphs.py
rdkit/Chem/Lipinski.py
rdkit/Chem/MACCSkeys.py
rdkit/Chem/MCS.py
rdkit/Chem/MolCatalog.py
rdkit/Chem/MolSurf.py
rdkit/Chem/PandasPatcher.py
rdkit/Chem/PandasTools.py
rdkit/Chem/PropertyMol.py
rdkit/Chem/PyMol.py
rdkit/Chem/QED.py
rdkit/Chem/Randomize.py
rdkit/Chem/Recap.py
rdkit/Chem/ReducedGraphs.py
rdkit/Chem/RegistrationHash.py
rdkit/Chem/SATIS.py
rdkit/Chem/SaltRemover.py
rdkit/Chem/ShowMols.py
rdkit/Chem/SpacialScore.py
rdkit/Chem/TemplateAlign.py
rdkit/Chem/TorsionFingerprints.py
rdkit/Chem/__init__.py
rdkit/Chem/inchi.py
rdkit/Chem/rdAbbreviations.so
rdkit/Chem/rdCIPLabeler.so
rdkit/Chem/rdChemDraw.so
rdkit/Chem/rdChemReactions.so
rdkit/Chem/rdChemicalFeatures.so
rdkit/Chem/rdCoordGen.so
rdkit/Chem/rdDepictor.so
rdkit/Chem/rdDeprotect.so
rdkit/Chem/rdDetermineBonds.so
rdkit/Chem/rdDistGeom.so
rdkit/Chem/rdEHTTools.so
rdkit/Chem/rdEnumerateStereoisomers.so
rdkit/Chem/rdFMCS.so
rdkit/Chem/rdFingerprintGenerator.so
rdkit/Chem/rdForceFieldHelpers.so
rdkit/Chem/rdFreeSASA.so
rdkit/Chem/rdGeneralizedSubstruct.so
rdkit/Chem/rdMHFPFingerprint.so
rdkit/Chem/rdMIF.so
rdkit/Chem/rdMMPA.so
rdkit-2025.9.4.dist-info/LICENSE.md
rdkit-2025.9.4.dist-info/METADATA
rdkit-2025.9.4.dist-info/WHEEL
rdkit-2025.9.4.dist-info/top_level.txt
rdkit-2025.9.4.dist-info/RECORD
rdkit-2025.9.4.dist-info/sboms/auditwheel.cdx.json
