Metadata-Version: 2.1
Name: rdkit
Version: 2025.9.4
Summary: A collection of chemoinformatics and machine-learning software written in C++ and Python
Home-page: https://github.com/kuelumbus/rdkit-pypi
Author: Christopher Kuenneth
Author-email: chris@kuenneth.dev
License: BSD-3-Clause
Project-URL: RDKit, http://rdkit.org/
Project-URL: RDKit on Github, https://github.com/rdkit/rdkit
License-File: LICENSE.md
Requires-Dist: numpy
Requires-Dist: Pillow
